{
  "indexes": [
    {
      "collectionGroup": "challenges",
      "queryScope": "COLLECTION",
      "fields": [
        {
          "fieldPath": "status",
          "order": "ASCENDING"
        },
        {
          "fieldPath": "endDate",
          "order": "ASCENDING"
        }
      ]
    },
    {
      "collectionGroup": "challenges",
      "queryScope": "COLLECTION",
      "fields": [
        {
          "fieldPath": "participantIds",
          "arrayConfig": "CONTAINS"
        },
        {
          "fieldPath": "createdAt",
          "order": "DESCENDING"
        }
      ]
    },
    {
      "collectionGroup": "leaderboard",
      "queryScope": "COLLECTION",
      "fields": [
        {
          "fieldPath": "wins",
          "order": "DESCENDING"
        },
        {
          "fieldPath": "totalEarnings",
          "order": "DESCENDING"
        }
      ]
    }
  ],
  "fieldOverrides": []
}
